{
    "name": "Flownau Dev",
    "dockerComposeFile": [
        "../docker-compose.yml"
    ],
    "service": "app",
    "workspaceFolder": "/app",
    "customizations": {
        "vscode": {
            "extensions": [
                "dbaeumer.vscode-eslint",
                "esbenp.prettier-vscode",
                "Prisma.prisma",
                "bradlc.vscode-tailwindcss"
            ],
            "settings": {
                "editor.formatOnSave": true,
                "terminal.integrated.defaultProfile.linux": "ash"
            }
        }
    },
    "remoteUser": "node"
}